{
  "main": {
    "id": "a8017cc2ee0e9476",
    "type": "split",
    "children": [
      {
        "id": "fbe5706f5cebe9ee",
        "type": "tabs",
        "children": [
          {
            "id": "275c867d96743d1d",
            "type": "leaf",
            "state": {
              "type": "markdown",
              "state": {
                "file": "01.TypeScript Basics/01.Introdução ao TS.md",
                "mode": "source",
                "source": false
              },
              "icon": "lucide-file",
              "title": "01.Introdução ao TS"
            }
          }
        ]
      }
    ],
    "direction": "vertical"
  },
  "left": {
    "id": "95edef668b657176",
    "type": "split",
    "children": [
      {
        "id": "fd926b8554709dde",
        "type": "tabs",
        "children": [
          {
            "id": "1b02efb55613b8a3",
            "type": "leaf",
            "state": {
              "type": "file-explorer",
              "state": {
                "sortOrder": "alphabetical",
                "autoReveal": true
              },
              "icon": "lucide-folder-closed",
              "title": "Explorador de arquivos"
            }
          },
          {
            "id": "fcf5211b07f910d2",
            "type": "leaf",
            "state": {
              "type": "search",
              "state": {
                "query": "rsm",
                "matchingCase": false,
                "explainSearch": false,
                "collapseAll": false,
                "extraContext": false,
                "sortOrder": "alphabetical"
              },
              "icon": "lucide-search",
              "title": "Procurar"
            }
          },
          {
            "id": "e7973939567207e7",
            "type": "leaf",
            "state": {
              "type": "markdown",
              "state": {
                "file": "5.Maio/🟢 Neppo.md",
                "mode": "source",
                "source": false
              },
              "icon": "lucide-file",
              "title": "🟢 Neppo"
            }
          },
          {
            "id": "2546ad1fa6d4380f",
            "type": "leaf",
            "state": {
              "type": "bookmarks",
              "state": {},
              "icon": "lucide-bookmark",
              "title": "Marcadores"
            }
          }
        ]
      }
    ],
    "direction": "horizontal",
    "width": 347.5
  },
  "right": {
    "id": "1b77f82fc4207f64",
    "type": "split",
    "children": [
      {
        "id": "ed9588303afd4cca",
        "type": "tabs",
        "children": [
          {
            "id": "a29bd78191eb249e",
            "type": "leaf",
            "state": {
              "type": "outline",
              "state": {
                "file": "01.TypeScript Basics/01.Introdução ao TS.md",
                "followCursor": false,
                "showSearch": false,
                "searchQuery": ""
              },
              "icon": "lucide-list",
              "title": "Sumário de 01.Introdução ao TS"
            }
          },
          {
            "id": "dbe9e1e4c0cb097a",
            "type": "leaf",
            "state": {
              "type": "backlink",
              "state": {
                "file": "React Hooks/1️⃣ Fundamentos dos Hooks.md",
                "collapseAll": false,
                "extraContext": false,
                "sortOrder": "alphabetical",
                "showSearch": false,
                "searchQuery": "",
                "backlinkCollapsed": false,
                "unlinkedCollapsed": true
              },
              "icon": "links-coming-in",
              "title": "Links inversos para 1️⃣ Fundamentos dos Hooks"
            }
          },
          {
            "id": "433c1db50f655ade",
            "type": "leaf",
            "state": {
              "type": "outgoing-link",
              "state": {
                "linksCollapsed": false,
                "unlinkedCollapsed": true
              },
              "icon": "links-going-out",
              "title": "Links de saída"
            }
          },
          {
            "id": "8683bbb36e1857f7",
            "type": "leaf",
            "state": {
              "type": "tag",
              "state": {
                "sortOrder": "frequency",
                "useHierarchy": true,
                "showSearch": false,
                "searchQuery": ""
              },
              "icon": "lucide-tags",
              "title": "Tags"
            }
          }
        ]
      }
    ],
    "direction": "horizontal",
    "width": 243.5
  },
  "left-ribbon": {
    "hiddenItems": {
      "switcher:Abrir a troca rápida": false,
      "graph:Abrir visualização em gráfico": false,
      "canvas:Criar novo canvas": false,
      "daily-notes:Abrir a nota de hoje": false,
      "templates:Inserir modelo": false,
      "command-palette:Abrir paleta de comandos": false
    }
  },
  "active": "275c867d96743d1d",
  "lastOpenFiles": [
    "13.Projetos Avançados do TypeScript/03.Contact Management System Using TypeScript.md",
    "13.Projetos Avançados do TypeScript/02.Task Management App Using TypeScript.md",
    "13.Projetos Avançados do TypeScript/01.Quiz App Using Typescript.md",
    "12.Fatos interessantes sobre o TypeScript/06.Fatos interessantes sobre módulos e namespaces no TypeScript.md",
    "12.Fatos interessantes sobre o TypeScript/05.Fatos interessantes sobre genéricos no TypeScript.md",
    "12.Fatos interessantes sobre o TypeScript/04.Fatos interessantes sobre classes e programação orientada a objetos no TypeScript.md",
    "12.Fatos interessantes sobre o TypeScript/03.Fatos interessantes sobre tipos de objetos e interfaces no TypeScript.md",
    "12.Fatos interessantes sobre o TypeScript/02.Fatos interessantes sobre funções no TypeScript.md",
    "12.Fatos interessantes sobre o TypeScript/01.Fatos interessantes sobre os fundamentos do TypeScript.md",
    "11.Configuração e desempenho do TypeScript/01.Ajuste de desempenho para compilação do TypeScript.md",
    "11.Configuração e desempenho do TypeScript/02.TypeScript Configuration & Performance Quiz.md",
    "10.TypeScript Testing/04.Testing with TypeScript Quiz.md",
    "11.Configuração e desempenho do TypeScript/01.Otimizando tsconfig.json para grandes projetos.md",
    "09.Módulos e namespaces TypeScript/02.O que é namespace em Typescript.md",
    "10.TypeScript Testing/03.Type-safe Mocking in TypeScript.md",
    "10.TypeScript Testing/02.Testando Frameworks in TypeScript.md",
    "10.TypeScript Testing/01.Escrevendo testes de unidade com TypeScript.md",
    "09.Módulos e namespaces TypeScript/03.Testing with TypeScript Quiz.md",
    "09.Módulos e namespaces TypeScript/01.Módulos TypeScript.md",
    "09.Módulos e namespaces TypeScript/02.Exportações padrão e nomeadas no TypeScript.md",
    "08.Tipos avançados de TypeScript/07.Advanced Types in TypeScript Quiz.md",
    "08.Tipos avançados de TypeScript/01.TS Type Assertions and Type Guards.md",
    "08.Tipos avançados de TypeScript/06.Tipos de utilitários TS.md",
    "05.Classes TypeScript e Programação Orientada a Objetos/07.TypeScript OOP Quiz.md",
    "06.TypeScript Generics/06.TypeScript Generics Quiz.md",
    "08.Tipos avançados de TypeScript/05.Tipos recursivos TS.md",
    "06.Junho",
    "1️⃣",
    "Junho 4️⃣",
    "05.Maio",
    "4️⃣",
    "3️⃣ Marco/Sem título"
  ]
}